CONTRIBUTING.md
HISTORY.md
LICENSE
MANIFEST.in
README.md
readme.md
setup.cfg
setup.py
docs/Makefile
docs/conf.py
docs/contributing.rst
docs/history.rst
docs/index.rst
docs/installation.rst
docs/make.bat
docs/modules.rst
docs/pyanzo.rst
docs/readme.rst
docs/usage.rst
pyanzo/__init__.py
pyanzo/anzo_client.py
pyanzo/anzo_request.py
pyanzo/graphmart_manager.py
pyanzo/lds_manager.py
pyanzo/orchestration_wrapper.py
pyanzo/quad_store.py
pyanzo/query_result.py
pyanzo/uris.py
pyanzo.egg-info/PKG-INFO
pyanzo.egg-info/SOURCES.txt
pyanzo.egg-info/dependency_links.txt
pyanzo.egg-info/not-zip-safe
pyanzo.egg-info/requires.txt
pyanzo.egg-info/top_level.txt
tests/__init__.py
tests/query.rq
tests/test_add_and_remove.py
tests/test_advanced.py
tests/test_auth.py
tests/test_basic.py
tests/test_common.py
tests/test_execute_semantic_service.py
tests/test_get.py
tests/test_graphmart_manager.py
tests/test_lds_manager.py
tests/test_orchestration_wrapper.py
tests/test_quad_store.py
tests/test_query_graphmart.py
tests/test_query_journal.py
tests/test_query_lds.py
tests/test_query_system_tables.py
tests/test_update_journal.py
tests/test_assets/gmart.trig
tests/test_assets/malformed_graphmart_query.rq
tests/test_assets/malformed_journal_query.rq
tests/test_assets/query_test_graphmart.sh
tests/test_assets/sample.json
tests/test_assets/sample.n3
tests/test_assets/sample.trig
tests/test_assets/sample.trix
tests/test_assets/sample.ttl
tests/test_assets/simple_graphmart_query.rq
tests/test_assets/simple_journal_query.rq
tests/test_assets/trig_with_bnodes.trig
tests/test_assets/empty_dataset/flds.trig
tests/test_assets/pyanzo_test_dataset/.lsdir
tests/test_assets/pyanzo_test_dataset/flds.trig
tests/test_assets/pyanzo_test_dataset/onts/.ontsdir
tests/test_assets/pyanzo_test_dataset/onts/PyAnzo_Dictionary_-_PyAnzo_Datasource_-_Auto.trig
tests/test_assets/pyanzo_test_dataset/rdf.ttl.gz/Loaddata_Person_734ff.ttl.gz/20200502131201.ttl.gz/..jobMetadata.crc
tests/test_assets/pyanzo_test_dataset/rdf.ttl.gz/Loaddata_Person_734ff.ttl.gz/20200502131201.ttl.gz/..lsdir.crc
tests/test_assets/pyanzo_test_dataset/rdf.ttl.gz/Loaddata_Person_734ff.ttl.gz/20200502131201.ttl.gz/.jobMetadata
