Metadata-Version: 2.1
Name: pyanzo
Version: 3.3.11
Summary: PyAnzo is a library for interacting with Anzo
Home-page: 
Author: Tommy Fang, William Ades, Curtis Galione, Andrew Parisi, Alex Ledger
Author-email: info@cambridgesemantics.com
Keywords: pyanzo
Classifier: Intended Audience :: Developers
Classifier: Natural Language :: English
Classifier: Programming Language :: Python :: 3
Classifier: Programming Language :: Python :: 3.5
Classifier: Programming Language :: Python :: 3.6
Classifier: Programming Language :: Python :: 3.7
Classifier: Programming Language :: Python :: 3.8
Classifier: Programming Language :: Python :: 3.9
Classifier: Programming Language :: Python :: 3.10
Requires-Python: >=3.5
License-File: LICENSE
